poetry_sort/__init__.py
poetry_sort/plugin.py
poetry_sort-2.0.0.dist-info/LICENSE.md
poetry_sort-2.0.0.dist-info/WHEEL
poetry_sort-2.0.0.dist-info/METADATA
poetry_sort-2.0.0.dist-info/entry_points.txt
poetry_sort-2.0.0.dist-info/RECORD
