Metadata-Version: 2.1
Name: poetry-sort
Version: 2.0.0
Summary: Alphabetically sort your Poetry dependencies
Home-page: https://github.com/celsiusnarhwal/poetry-sort
License: MIT
Keywords: poetry,sort,dependencies
Author: celsius narhwal
Author-email: hello@celsiusnarhwal.dev
Requires-Python: >=3.8,<4.0
Classifier: License :: OSI Approved :: MIT License
Classifier: Programming Language :: Python :: 3
Classifier: Programming Language :: Python :: 3.8
Classifier: Programming Language :: Python :: 3.9
Classifier: Programming Language :: Python :: 3.10
Classifier: Programming Language :: Python :: 3.11
Requires-Dist: dict-deep (>=4.1.2,<5.0.0)
Requires-Dist: poetry (>=1.2,<2.0)
Requires-Dist: pydantic (>=1.10.2,<2.0.0)
